on_n_scraper/__init__.py
on_n_scraper/base.py
on_n_scraper/urls.py
on_n_scraper_hitnik-0.0.1.dist-info/LICENSE
on_n_scraper_hitnik-0.0.1.dist-info/METADATA
on_n_scraper_hitnik-0.0.1.dist-info/WHEEL
on_n_scraper_hitnik-0.0.1.dist-info/top_level.txt
on_n_scraper_hitnik-0.0.1.dist-info/RECORD
